binutils/__init__.py
binutils/core.py
binutils-0.3.dev0.dist-info/AUTHORS
binutils-0.3.dev0.dist-info/LICENSE
binutils-0.3.dev0.dist-info/METADATA
binutils-0.3.dev0.dist-info/WHEEL
binutils-0.3.dev0.dist-info/top_level.txt
binutils-0.3.dev0.dist-info/RECORD
