Metadata-Version: 2.1
Name: binutils
Version: 0.3.dev0
Summary: Python Binary Tools
Author-email: Jérémie DECOCK <jeremie.decock@accenta.ai>
Classifier: Development Status :: 4 - Beta
Classifier: Intended Audience :: Developers
Classifier: Natural Language :: English
Classifier: Operating System :: OS Independent
Classifier: Programming Language :: Python :: 3
Classifier: Topic :: Software Development :: Libraries
Classifier: Topic :: Software Development :: Libraries :: Python Modules
Requires-Python: >=3.8
License-File: LICENSE
License-File: AUTHORS
